setup.py
news/__init__.py
news/admin.py
news/feeds.py
news/fields.py
news/models.py
news/urls.py
news/views.py
news/tests/__init__.py
news/tests/urls.py
zamtools_news.egg-info/PKG-INFO
zamtools_news.egg-info/SOURCES.txt
zamtools_news.egg-info/dependency_links.txt
zamtools_news.egg-info/top_level.txt