Metadata-Version: 1.0
Name: zamtools-news
Version: 0.9
Summary: Django application for generating a simple news feed.
Home-page: http://code.google.com/p/zamtools-news/
Author: Ian Zamojc
Author-email: zamtools@zamtools.com
License: UNKNOWN
Platform: UNKNOWN
